{
  "greetings": [
    "Hi!",
    "Hello!",
    "Good morning!",
    "Good afternoon!",
    "Good evening!",
    "Hey there!",
    "What's up?",
    "Howdy!",
    "Yo!",
    "Hiya!",
    "Greetings!",
    "Welcome!",
    "Nice to see you!",
    "Long time!",
    "Hey friend!"
  ],
  "questions": [
    "How are you?",
    "Want to play?",
    "Are you busy?",
    "What are you doing?",
    "How's your pet?",
    "Want to chat?",
    "What's new?",
    "Where are you?",
    "Did you see that?",
    "Can you help?",
    "Want to trade?",
    "Got time?",
    "Are you there?",
    "What happened?",
    "Guess what?"
  ],
  "responses": [
    "Yes",
    "No",
    "Maybe",
    "OK",
    "Sure!",
    "Nope",
    "Sounds good!",
    "I don't know",
    "I guess",
    "Definitely!",
    "Absolutely not",
    "Whatever"
  ],
  "emotions": [
    "I'm happy!",
    "Feeling sad",
    "So excited!",
    "I'm tired",
    "Feeling great!",
    "Not good",
    "Amazing day!",
    "Stressed out",
    "Bored",
    "Super happy!",
    "Feeling sick",
    "Love this!",
    "Hate this!",
    "Surprised!",
    "Confused"
  ],
  "activities": [
    "Playing now",
    "Time to eat!",
    "Going to sleep",
    "Studying",
    "Watching TV",
    "Reading",
    "At school",
    "At home",
    "Outside",
    "Shopping",
    "Busy right now",
    "Free now",
    "Working",
    "Relaxing",
    "Exercising"
  ],
  "fun": [
    "LOL",
    "OMG",
    "Cool!",
    "Awesome!",
    "Amazing!",
    "No way!",
    "Seriously?",
    "Wow!",
    "That's funny!",
    "So true!",
    "I can't even",
    "For real?",
    "Same here!",
    "Totally!",
    "Epic!"
  ],
  "social": [
    "Thanks!",
    "You're welcome",
    "Sorry!",
    "No problem",
    "Congrats!",
    "Good luck!",
    "See you later!",
    "Bye!",
    "Good night!",
    "Take care!",
    "Miss you!",
    "Thinking of you",
    "You rock!"
  ]
}
